dslr/__init__.py
dslr/cli.py
dslr/config.py
dslr/console.py
dslr/operations.py
dslr/pg_client.py
dslr/runner.py
dslr-0.6.0.dist-info/LICENSE
dslr-0.6.0.dist-info/METADATA
dslr-0.6.0.dist-info/WHEEL
dslr-0.6.0.dist-info/entry_points.txt
dslr-0.6.0.dist-info/RECORD
