Metadata-Version: 2.3
Name: DSLR
Version: 0.6.0
Summary: Take lightning fast snapshots of your local Postgres databases.
License: MIT
Keywords: database,snapshot,backup
Author: Mitchel Cabuloy
Author-email: mixxorz@gmail.com
Requires-Python: >=3.9,<4.0
Classifier: Development Status :: 3 - Alpha
Classifier: Intended Audience :: Developers
Classifier: License :: OSI Approved :: MIT License
Classifier: Operating System :: OS Independent
Classifier: Programming Language :: Python :: 3
Classifier: Programming Language :: Python :: 3.9
Classifier: Programming Language :: Python :: 3.10
Classifier: Programming Language :: Python :: 3.11
Classifier: Programming Language :: Python :: 3.12
Classifier: Programming Language :: Python :: 3.13
Classifier: Topic :: Database
Provides-Extra: psycopg
Provides-Extra: psycopg2
Provides-Extra: psycopg2-binary
Requires-Dist: click (>=8.1.3,<9.0.0)
Requires-Dist: psycopg (>=3.1.14,<4.0.0) ; extra == "psycopg"
Requires-Dist: psycopg2 (>=2.9.3,<3.0.0) ; extra == "psycopg2"
Requires-Dist: psycopg2-binary (>=2.9.3,<3.0.0) ; extra == "psycopg2-binary"
Requires-Dist: rich (>=13.8.1,<14.0.0)
Requires-Dist: timeago (>=1.0.15,<2.0.0)
Requires-Dist: tomli (>=2.0.1,<3.0.0)
Project-URL: Homepage, https://github.com/mixxorz/DSLR
Project-URL: Repository, https://github.com/mixxorz/DSLR
